{"sits":[
{"name":"a1","x":70, "y":50 ,"rotate":"90","status":true},
{"name":"a2","x":70, "y":100,"rotate":"90","status":true},
{"name":"a3","x":70, "y":150,"rotate":"90","status":false},

{"name":"b1","x":140,"y":50 ,"rotate":"90","status":true},
{"name":"b2","x":140,"y":100,"rotate":"90","status":true},
{"name":"b3","x":140,"y":150,"rotate":"90","status":false},

{"name":"c1","x":210, "y":50 ,"rotate":"90","status":true},
{"name":"c2","x":210, "y":100,"rotate":"90","status":true},
{"name":"c3","x":210 ,"y":150,"rotate":"90","status":false},

{"name":"d1","x":280, "y":50 ,"rotate":"90","status":true},
{"name":"d2","x":280, "y":100,"rotate":"90","status":true},
{"name":"d3","x":280 ,"y":150,"rotate":"90","status":false},

{"name":"e1","x":350, "y":50 ,"rotate":"90","status":true},
{"name":"e2","x":350, "y":100,"rotate":"90","status":true},
{"name":"e3","x":350 ,"y":150,"rotate":"90","status":false},

{"name":"f1","x":420, "y":50 ,"rotate":"90","status":true},
{"name":"f2","x":420, "y":100,"rotate":"90","status":true},
{"name":"f3","x":420 ,"y":150,"rotate":"90","status":false},

{"name":"g1","x":490, "y":50 ,"rotate":"90","status":true},
{"name":"g2","x":490, "y":100,"rotate":"90","status":true},
{"name":"g3","x":490 ,"y":150,"rotate":"90","status":false},

{"name":"h1","x":560, "y":50 ,"rotate":"90","status":true},
{"name":"h2","x":560, "y":100,"rotate":"90","status":true},
{"name":"h3","x":560 ,"y":150,"rotate":"90","status":false},

{"name":"i1","x":630, "y":50 ,"rotate":"90","status":true},
{"name":"i2","x":630, "y":100,"rotate":"90","status":true},
{"name":"i3","x":630 ,"y":150,"rotate":"90","status":false},

{"name":"j1","x":700, "y":50 ,"rotate":"90","status":true},
{"name":"j2","x":700, "y":100,"rotate":"90","status":true},
{"name":"j3","x":700 ,"y":150,"rotate":"90","status":false},

{"name":"k1","x":770, "y":50 ,"rotate":"90","status":true},
{"name":"k2","x":770, "y":100,"rotate":"90","status":true},
{"name":"k3","x":770 ,"y":150,"rotate":"90","status":false},

{"name":"b1","x":45, "y":80 ,"rotate":"90","status":true},
{"name":"b2","x":88, "y":80 ,"rotate":"90","status":true},
{"name":"b3","x":140,"y":80 ,"rotate":"90","status":false},
{"name":"c1","x":45, "y":120,"rotate":"90","status":false},
{"name":"c2","x":88, "y":120,"rotate":"90","status":true},
{"name":"c3","x":140,"y":120,"rotate":"90","status":true},
{"name":"d1","x":45, "y":160,"rotate":"90","status":true},
{"name":"d2","x":88, "y":160,"rotate":"90","status":false},
{"name":"d3","x":140,"y":160,"rotate":"90","status":true},
{"name":"e1","x":45, "y":200,"rotate":"90","status":true},
{"name":"e2","x":88, "y":200,"rotate":"90","status":true},
{"name":"e3","x":140,"y":200,"rotate":"90","status":true},
{"name":"f1","x":45, "y":240,"rotate":"90","status":true},
{"name":"f2","x":88, "y":240,"rotate":"90","status":false},
{"name":"f3","x":140,"y":240,"rotate":"90","status":true},
{"name":"g1","x":140,"y":200,"rotate":"0","status":false},
{"name":"a1","x":320,"y":230,"rotate":"0","status":true}


]}

